uniocsone/__init__.py
uniocsone/uniocsone.py
uniocsone-0.0.5.dist-info/LICENSE
uniocsone-0.0.5.dist-info/METADATA
uniocsone-0.0.5.dist-info/WHEEL
uniocsone-0.0.5.dist-info/top_level.txt
uniocsone-0.0.5.dist-info/RECORD
